LICENSE.txt
MANIFEST.in
README.md
setup.cfg
setup.py
yt_archiver.egg-info/PKG-INFO
yt_archiver.egg-info/SOURCES.txt
yt_archiver.egg-info/dependency_links.txt
yt_archiver.egg-info/entry_points.txt
yt_archiver.egg-info/requires.txt
yt_archiver.egg-info/top_level.txt
ytarchiver/__init__.py
ytarchiver/api.py
ytarchiver/args.py
ytarchiver/common.py
ytarchiver/download.py
ytarchiver/lookup.py
ytarchiver/main.py
ytarchiver/recording.py
ytarchiver/sqlite.py