Metadata-Version: 1.1
Name: yt-archiver
Version: 0.5.0
Summary: Daemon for monitoring YouTube channels for new videos. Offers automatic backup of uploaded content
Home-page: https://github.com/mkorman9/yt-archiver
Author: Michal Korman
Author-email: michal.korman@icloud.com
License: MIT License
